odoo/addons/animal/README.rst
odoo/addons/animal/__init__.py
odoo/addons/animal/__manifest__.py
odoo/addons/animal/data/animal.breed.csv
odoo/addons/animal/data/animal.color.csv
odoo/addons/animal/data/animal.species.csv
odoo/addons/animal/data/ir.module.category.csv
odoo/addons/animal/i18n/animal.pot
odoo/addons/animal/i18n/es.po
odoo/addons/animal/i18n/fr.po
odoo/addons/animal/i18n/fr_FR.po
odoo/addons/animal/models/__init__.py
odoo/addons/animal/models/animal.py
odoo/addons/animal/models/animal_breed.py
odoo/addons/animal/models/animal_color.py
odoo/addons/animal/models/animal_species.py
odoo/addons/animal/readme/CONTRIBUTORS.rst
odoo/addons/animal/readme/DESCRIPTION.rst
odoo/addons/animal/readme/USAGE.rst
odoo/addons/animal/security/ir.model.access.csv
odoo/addons/animal/security/res_groups.xml
odoo/addons/animal/static/description/icon.png
odoo/addons/animal/static/description/index.html
odoo/addons/animal/static/img/avatar.png
odoo/addons/animal/views/animal.xml
odoo/addons/animal/views/animal_breed.xml
odoo/addons/animal/views/animal_color.xml
odoo/addons/animal/views/animal_species.xml
odoo/addons/animal/views/menu.xml
odoo14_addon_animal-14.0.1.2.0.dist-info/METADATA
odoo14_addon_animal-14.0.1.2.0.dist-info/WHEEL
odoo14_addon_animal-14.0.1.2.0.dist-info/top_level.txt
odoo14_addon_animal-14.0.1.2.0.dist-info/RECORD
